pipyabc/__init__.py
pipyabc/abc.py
pipyabc-0.2.4.dist-info/METADATA
pipyabc-0.2.4.dist-info/WHEEL
pipyabc-0.2.4.dist-info/RECORD
