Metadata-Version: 2.3
Name: pipyabc
Version: 0.2.4
Summary: Hermes - A python package towards an ultimate high-performance algorithm for cosmic statistics of large data sets
Author-email: PyHermes Team <15997232823@163.com>
Maintainer-email: Tristan <15997232823@163.com>, Ding ding <dingdluan@gmail.com>, feng <hhh@163.com>
License: MIT
Keywords: correlation-function,cosmology,large-structure,nbody,statistics
Classifier: License :: OSI Approved :: MIT License
Classifier: Operating System :: OS Independent
Classifier: Programming Language :: Python :: 3
Requires-Python: >=3.6
Requires-Dist: json5
Requires-Dist: mpi4py
Requires-Dist: numba
Requires-Dist: numpy
Requires-Dist: pywavelets
Requires-Dist: requests
Requires-Dist: rich
Requires-Dist: scipy
Requires-Dist: termcolor==1.1.0
